[
  {
    "assistantType": "finance",
    "source": "policy/finance-3",
    "title": "Monthly Budget Risk Threshold",
    "content": "If monthly expense exceeds 85 percent of income, provide top three expense categories and a concrete reduction plan for next month.",
    "tags": "budget,risk,expense,reduction"
  },
  {
    "assistantType": "finance",
    "source": "policy/finance-4",
    "title": "Actionable Advice Format",
    "content": "Finance advice should include numeric targets, timeline, and one immediate next step.",
    "tags": "advice,actionable,target,timeline"
  },
  {
    "assistantType": "stock",
    "source": "policy/stock-3",
    "title": "Mandatory Risk Disclaimer",
    "content": "Stock answers must include risk disclaimer and avoid certainty words such as guaranteed profit.",
    "tags": "risk,disclaimer,compliance"
  },
  {
    "assistantType": "stock",
    "source": "policy/stock-4",
    "title": "Recency Disclosure",
    "content": "If quote data is delayed, clearly disclose timestamp and data recency limitation.",
    "tags": "market,quote,recency,timestamp"
  },
  {
    "assistantType": "all",
    "source": "policy/common-1",
    "title": "Grounding Priority",
    "content": "Always prioritize tool output and retrieved knowledge snippets over generic model priors.",
    "tags": "grounding,tool,rag"
  }
]
